{
	"debug_type": "enter_view_transforms",
	"json_path": "../../../../UE_Proj/Test_0529_1510/Saved/FromLZCaptures/FromLZ_20260607_234510_debug_transforms.json",
	"scene_capture_context": "CaptureLineArtPng",
	"player_camera_manager_source": "PlayerCameraManager->GetCameraLocation/Rotation",
	"fromlz_component_source": "FromLZ->GetComponentTransform()",
	"source_view_source": "FromLZ orthographic camera component",
	"orthographic_capture_view_source": "FromLZ orthographic camera component",
	"orthographic_framing_mode": "stable_viewport_final_projection_matrix",
	"focus_source": "FromLZ orthographic camera forward reference",
	"scene_capture_source": "SceneCapture->GetComponentTransform()",
	"source_view_projection_type": "ECameraProjectionMode::Orthographic",
	"scene_capture_projection_type": "ECameraProjectionMode::Orthographic",
	"scene_capture_fov": 90,
	"scene_capture_ortho_width": 1536,
	"scene_capture_auto_calculate_ortho_planes": false,
	"scene_capture_auto_plane_shift": 0,
	"scene_capture_update_ortho_planes": false,
	"scene_capture_use_camera_height_as_view_target": false,
	"scene_capture_uses_custom_projection_matrix": true,
	"scene_capture_projection_matrix_source": "stable_orthographic_viewport_final_projection_matrix",
	"stable_viewport_projection_matrix":
	{
		"row_0": [
			0.00087142530267189937,
			0,
			0,
			0
		],
		"row_1": [
			0,
			0.0013020833333333333,
			0,
			0
		],
		"row_2": [
			0,
			0,
			-4.76837158203125e-07,
			0
		],
		"row_3": [
			0,
			0,
			1,
			1
		]
	},
	"scene_capture_custom_projection_matrix":
	{
		"row_0": [
			0.00087142530267189937,
			0,
			0,
			0
		],
		"row_1": [
			0,
			0.0013020833333333333,
			0,
			0
		],
		"row_2": [
			0,
			0,
			-4.76837158203125e-07,
			0
		],
		"row_3": [
			0,
			0,
			1,
			1
		]
	},
	"scene_capture_projection_matrix_matches_stable_viewport": true,
	"orthographic_focus_depth": 768,
	"orthographic_backoff": 0,
	"orthographic_focus_point_x": -437.61077950456075,
	"orthographic_focus_point_y": -798.39660817363711,
	"orthographic_focus_point_z": 490.94550947322671,
	"player_camera_manager_available": true,
	"player_camera_manager_transform":
	{
		"location_x": -671.31718871997953,
		"location_y": -1502.4524285263358,
		"location_z": 689.7185361119632,
		"pitch": -15.000000000000009,
		"yaw": 71.636774675290468,
		"roll": 8.2318812555273957e-16,
		"scale_x": 1,
		"scale_y": 1,
		"scale_z": 1
	},
	"fromlz_component_transform":
	{
		"location_x": -671.31718871997953,
		"location_y": -1502.4524285263358,
		"location_z": 689.7185361119632,
		"pitch": -15.000000000000018,
		"yaw": 71.636774675290539,
		"roll": -8.2318812555273957e-16,
		"scale_x": 1,
		"scale_y": 1,
		"scale_z": 1
	},
	"source_view_transform":
	{
		"location_x": -671.31718871997953,
		"location_y": -1502.4524285263358,
		"location_z": 689.7185361119632,
		"pitch": -15.000000000000018,
		"yaw": 71.636774675290539,
		"roll": -8.2318812555273957e-16,
		"scale_x": 1,
		"scale_y": 1,
		"scale_z": 1
	},
	"orthographic_capture_view_transform":
	{
		"location_x": -671.31718871997953,
		"location_y": -1502.4524285263358,
		"location_z": 689.7185361119632,
		"pitch": -15.000000000000018,
		"yaw": 71.636774675290539,
		"roll": -8.2318812555273957e-16,
		"scale_x": 1,
		"scale_y": 1,
		"scale_z": 1
	},
	"scene_capture_transform":
	{
		"location_x": -671.31718871997953,
		"location_y": -1502.4524285263358,
		"location_z": 689.7185361119632,
		"pitch": -15.000000000000057,
		"yaw": 71.636774675290624,
		"roll": -8.2318812555273976e-16,
		"scale_x": 1,
		"scale_y": 1,
		"scale_z": 1
	},
	"scene_capture_matches_fromlz_component_pose": true,
	"scene_capture_matches_orthographic_capture_view_pose": true,
	"scene_capture_minus_fromlz_component":
	{
		"location_delta_x": 0,
		"location_delta_y": 0,
		"location_delta_z": 0,
		"location_distance": 0,
		"pitch_delta": -5.6843418860808015e-14,
		"yaw_delta": 8.5265128291212022e-14,
		"roll_delta": 0,
		"scale_delta_x": 0,
		"scale_delta_y": 0,
		"scale_delta_z": 0
	},
	"scene_capture_minus_orthographic_capture_view":
	{
		"location_delta_x": 0,
		"location_delta_y": 0,
		"location_delta_z": 0,
		"location_distance": 0,
		"pitch_delta": -5.6843418860808015e-14,
		"yaw_delta": 8.5265128291212022e-14,
		"roll_delta": 0,
		"scale_delta_x": 0,
		"scale_delta_y": 0,
		"scale_delta_z": 0
	},
	"player_camera_manager_matches_fromlz_component_pose": true,
	"scene_capture_matches_player_camera_manager_pose": true,
	"fromlz_component_minus_player_camera_manager":
	{
		"location_delta_x": 0,
		"location_delta_y": 0,
		"location_delta_z": 0,
		"location_distance": 0,
		"pitch_delta": 0,
		"yaw_delta": 7.1054273576010019e-14,
		"roll_delta": 0,
		"scale_delta_x": 0,
		"scale_delta_y": 0,
		"scale_delta_z": 0
	},
	"scene_capture_minus_player_camera_manager":
	{
		"location_delta_x": 0,
		"location_delta_y": 0,
		"location_delta_z": 0,
		"location_distance": 0,
		"pitch_delta": -5.6843418860808015e-14,
		"yaw_delta": 1.5631940186722204e-13,
		"roll_delta": 0,
		"scale_delta_x": 0,
		"scale_delta_y": 0,
		"scale_delta_z": 0
	},
	"debug_version": 2,
	"outputs_generated": true,
	"capture_succeeded": true,
	"orthographic_frames_rendered": 122,
	"restored_perspective_frames_rendered": 1,
	"orthographic_settle_seconds": 2.0071269981563091,
	"view_origin_shift_prevention":
	{
		"policy": "disable_ortho_auto_planes_and_view_origin_correction",
		"auto_calculate_ortho_planes": false,
		"auto_plane_shift": 0,
		"update_ortho_planes": false,
		"use_camera_height_as_view_target": false,
		"ortho_near_clip_plane": 0,
		"ortho_far_clip_plane": 2097152
	},
	"stages":
	{
		"perspective_before_switch":
		{
			"stage": "perspective_before_switch",
			"pawn_transform":
			{
				"location_x": -306.15092432089057,
				"location_y": -402.36520922524483,
				"location_z": 379.13568198893745,
				"pitch": 0,
				"yaw": 63.902479999999954,
				"roll": 0,
				"scale_x": 1,
				"scale_y": 1,
				"scale_z": 1
			},
			"camera_component_transform":
			{
				"location_x": -671.31718871997953,
				"location_y": -1502.4524285263358,
				"location_z": 689.7185361119632,
				"pitch": -15.000000000000018,
				"yaw": 71.636774675290539,
				"roll": -8.2318812555273957e-16,
				"scale_x": 1,
				"scale_y": 1,
				"scale_z": 1
			},
			"camera_component_projection":
			{
				"projection_mode": "ECameraProjectionMode::Perspective",
				"field_of_view": 90,
				"ortho_width": 1536,
				"ortho_near_clip_plane": -768,
				"ortho_far_clip_plane": 2097152,
				"auto_plane_shift": 0,
				"aspect_ratio": 1.7777780294418335,
				"auto_calculate_ortho_planes": true,
				"update_ortho_planes": true,
				"use_camera_height_as_view_target": true,
				"constrain_aspect_ratio": false
			},
			"camera_boom_available": true,
			"camera_boom_transform":
			{
				"location_x": -306.15092432089057,
				"location_y": -402.36520922524483,
				"location_z": 379.13568198893745,
				"pitch": -15.000000000000046,
				"yaw": 71.636774675290667,
				"roll": 0,
				"scale_x": 1,
				"scale_y": 1,
				"scale_z": 1
			},
			"player_camera_manager_available": true,
			"player_camera_manager_view":
			{
				"transform":
				{
					"location_x": -671.31718871997953,
					"location_y": -1502.4524285263358,
					"location_z": 689.7185361119632,
					"pitch": -15.000000000000009,
					"yaw": 71.636774675290468,
					"roll": 8.2318812555273957e-16,
					"scale_x": 1,
					"scale_y": 1,
					"scale_z": 1
				},
				"projection_mode": "ECameraProjectionMode::Perspective",
				"field_of_view": 90,
				"ortho_width": 1536,
				"ortho_near_clip_plane": -768,
				"ortho_far_clip_plane": 2097152,
				"auto_plane_shift": 0,
				"aspect_ratio": 1.7777780294418335,
				"auto_calculate_ortho_planes": true,
				"update_ortho_planes": true,
				"use_camera_height_as_view_target": true,
				"constrain_aspect_ratio": false
			},
			"projection_data_available": true,
			"final_view_origin":
			{
				"value_x": -671.31718871997953,
				"value_y": -1502.4524285263358,
				"value_z": 689.7185361119632
			},
			"camera_to_view_target":
			{
				"value_x": 0,
				"value_y": 0,
				"value_z": 0
			},
			"final_view_rotation_matrix":
			{
				"row_0": [
					-0.94907842305774293,
					0.081538331711158818,
					0.3043051878427136,
					0
				],
				"row_1": [
					0.31503991316375796,
					0.24563957786187021,
					0.91673935821563513,
					0
				],
				"row_2": [
					1.3877788166908646e-17,
					0.9659258244035116,
					-0.25881905213951456,
					0
				],
				"row_3": [
					0,
					0,
					0,
					1
				]
			},
			"final_projection_matrix":
			{
				"row_0": [
					1.1897861714690126,
					0,
					0,
					0
				],
				"row_1": [
					0,
					1.7777779394035089,
					0,
					0
				],
				"row_2": [
					0,
					0,
					0,
					1
				],
				"row_3": [
					0,
					0,
					10,
					0
				]
			},
			"view_rect_min_x": 0,
			"view_rect_min_y": 0,
			"view_rect_max_x": 2576,
			"view_rect_max_y": 1724,
			"constrained_view_rect_min_x": 0,
			"constrained_view_rect_min_y": 0,
			"constrained_view_rect_max_x": 2576,
			"constrained_view_rect_max_y": 1724,
			"final_view_origin_minus_camera_component_x": 0,
			"final_view_origin_minus_camera_component_y": 0,
			"final_view_origin_minus_camera_component_z": 0,
			"final_view_origin_minus_player_camera_manager_x": 0,
			"final_view_origin_minus_player_camera_manager_y": 0,
			"final_view_origin_minus_player_camera_manager_z": 0
		},
		"orthographic_first_rendered_frame":
		{
			"stage": "orthographic_first_rendered_frame",
			"pawn_transform":
			{
				"location_x": -306.15092432089057,
				"location_y": -402.36520922524483,
				"location_z": 379.13568198893745,
				"pitch": 0,
				"yaw": 63.902479999999954,
				"roll": 0,
				"scale_x": 1,
				"scale_y": 1,
				"scale_z": 1
			},
			"camera_component_transform":
			{
				"location_x": -671.31718871997953,
				"location_y": -1502.4524285263358,
				"location_z": 689.7185361119632,
				"pitch": -15.000000000000018,
				"yaw": 71.636774675290539,
				"roll": -8.2318812555273957e-16,
				"scale_x": 1,
				"scale_y": 1,
				"scale_z": 1
			},
			"camera_component_projection":
			{
				"projection_mode": "ECameraProjectionMode::Orthographic",
				"field_of_view": 90,
				"ortho_width": 1536,
				"ortho_near_clip_plane": 0,
				"ortho_far_clip_plane": 2097152,
				"auto_plane_shift": 0,
				"aspect_ratio": 1.7777780294418335,
				"auto_calculate_ortho_planes": false,
				"update_ortho_planes": false,
				"use_camera_height_as_view_target": false,
				"constrain_aspect_ratio": false
			},
			"camera_boom_available": true,
			"camera_boom_transform":
			{
				"location_x": -306.15092432089057,
				"location_y": -402.36520922524483,
				"location_z": 379.13568198893745,
				"pitch": -15.000000000000046,
				"yaw": 71.636774675290667,
				"roll": 0,
				"scale_x": 1,
				"scale_y": 1,
				"scale_z": 1
			},
			"player_camera_manager_available": true,
			"player_camera_manager_view":
			{
				"transform":
				{
					"location_x": -671.31718871997953,
					"location_y": -1502.4524285263358,
					"location_z": 689.7185361119632,
					"pitch": -15.000000000000009,
					"yaw": 71.636774675290468,
					"roll": 8.2318812555273957e-16,
					"scale_x": 1,
					"scale_y": 1,
					"scale_z": 1
				},
				"projection_mode": "ECameraProjectionMode::Orthographic",
				"field_of_view": 90,
				"ortho_width": 1536,
				"ortho_near_clip_plane": 0,
				"ortho_far_clip_plane": 2097152,
				"auto_plane_shift": 0,
				"aspect_ratio": 1.7777780294418335,
				"auto_calculate_ortho_planes": false,
				"update_ortho_planes": false,
				"use_camera_height_as_view_target": false,
				"constrain_aspect_ratio": false
			},
			"projection_data_available": true,
			"final_view_origin":
			{
				"value_x": -671.31718871997953,
				"value_y": -1502.4524285263358,
				"value_z": 689.7185361119632
			},
			"camera_to_view_target":
			{
				"value_x": 0,
				"value_y": 0,
				"value_z": 0
			},
			"final_view_rotation_matrix":
			{
				"row_0": [
					-0.94907842305774293,
					0.081538331711158818,
					0.3043051878427136,
					0
				],
				"row_1": [
					0.31503991316375796,
					0.24563957786187021,
					0.91673935821563513,
					0
				],
				"row_2": [
					1.3877788166908646e-17,
					0.9659258244035116,
					-0.25881905213951456,
					0
				],
				"row_3": [
					0,
					0,
					0,
					1
				]
			},
			"final_projection_matrix":
			{
				"row_0": [
					0.00087142530267189937,
					0,
					0,
					0
				],
				"row_1": [
					0,
					0.0013020833333333333,
					0,
					0
				],
				"row_2": [
					0,
					0,
					-4.76837158203125e-07,
					0
				],
				"row_3": [
					0,
					0,
					1,
					1
				]
			},
			"view_rect_min_x": 0,
			"view_rect_min_y": 0,
			"view_rect_max_x": 2576,
			"view_rect_max_y": 1724,
			"constrained_view_rect_min_x": 0,
			"constrained_view_rect_min_y": 0,
			"constrained_view_rect_max_x": 2576,
			"constrained_view_rect_max_y": 1724,
			"final_view_origin_minus_camera_component_x": 0,
			"final_view_origin_minus_camera_component_y": 0,
			"final_view_origin_minus_camera_component_z": 0,
			"final_view_origin_minus_player_camera_manager_x": 0,
			"final_view_origin_minus_player_camera_manager_y": 0,
			"final_view_origin_minus_player_camera_manager_z": 0
		},
		"orthographic_stable_after_wait":
		{
			"stage": "orthographic_stable_after_wait",
			"pawn_transform":
			{
				"location_x": -306.15092432089057,
				"location_y": -402.36520922524483,
				"location_z": 379.13568198893745,
				"pitch": 0,
				"yaw": 63.902479999999954,
				"roll": 0,
				"scale_x": 1,
				"scale_y": 1,
				"scale_z": 1
			},
			"camera_component_transform":
			{
				"location_x": -671.31718871997953,
				"location_y": -1502.4524285263358,
				"location_z": 689.7185361119632,
				"pitch": -15.000000000000018,
				"yaw": 71.636774675290539,
				"roll": -8.2318812555273957e-16,
				"scale_x": 1,
				"scale_y": 1,
				"scale_z": 1
			},
			"camera_component_projection":
			{
				"projection_mode": "ECameraProjectionMode::Orthographic",
				"field_of_view": 90,
				"ortho_width": 1536,
				"ortho_near_clip_plane": 0,
				"ortho_far_clip_plane": 2097152,
				"auto_plane_shift": 0,
				"aspect_ratio": 1.7777780294418335,
				"auto_calculate_ortho_planes": false,
				"update_ortho_planes": false,
				"use_camera_height_as_view_target": false,
				"constrain_aspect_ratio": false
			},
			"camera_boom_available": true,
			"camera_boom_transform":
			{
				"location_x": -306.15092432089057,
				"location_y": -402.36520922524483,
				"location_z": 379.13568198893745,
				"pitch": -15.000000000000046,
				"yaw": 71.636774675290667,
				"roll": 0,
				"scale_x": 1,
				"scale_y": 1,
				"scale_z": 1
			},
			"player_camera_manager_available": true,
			"player_camera_manager_view":
			{
				"transform":
				{
					"location_x": -671.31718871997953,
					"location_y": -1502.4524285263358,
					"location_z": 689.7185361119632,
					"pitch": -15.000000000000009,
					"yaw": 71.636774675290468,
					"roll": 8.2318812555273957e-16,
					"scale_x": 1,
					"scale_y": 1,
					"scale_z": 1
				},
				"projection_mode": "ECameraProjectionMode::Orthographic",
				"field_of_view": 90,
				"ortho_width": 1536,
				"ortho_near_clip_plane": 0,
				"ortho_far_clip_plane": 2097152,
				"auto_plane_shift": 0,
				"aspect_ratio": 1.7777780294418335,
				"auto_calculate_ortho_planes": false,
				"update_ortho_planes": false,
				"use_camera_height_as_view_target": false,
				"constrain_aspect_ratio": false
			},
			"projection_data_available": true,
			"final_view_origin":
			{
				"value_x": -671.31718871997953,
				"value_y": -1502.4524285263358,
				"value_z": 689.7185361119632
			},
			"camera_to_view_target":
			{
				"value_x": 0,
				"value_y": 0,
				"value_z": 0
			},
			"final_view_rotation_matrix":
			{
				"row_0": [
					-0.94907842305774293,
					0.081538331711158818,
					0.3043051878427136,
					0
				],
				"row_1": [
					0.31503991316375796,
					0.24563957786187021,
					0.91673935821563513,
					0
				],
				"row_2": [
					1.3877788166908646e-17,
					0.9659258244035116,
					-0.25881905213951456,
					0
				],
				"row_3": [
					0,
					0,
					0,
					1
				]
			},
			"final_projection_matrix":
			{
				"row_0": [
					0.00087142530267189937,
					0,
					0,
					0
				],
				"row_1": [
					0,
					0.0013020833333333333,
					0,
					0
				],
				"row_2": [
					0,
					0,
					-4.76837158203125e-07,
					0
				],
				"row_3": [
					0,
					0,
					1,
					1
				]
			},
			"view_rect_min_x": 0,
			"view_rect_min_y": 0,
			"view_rect_max_x": 2576,
			"view_rect_max_y": 1724,
			"constrained_view_rect_min_x": 0,
			"constrained_view_rect_min_y": 0,
			"constrained_view_rect_max_x": 2576,
			"constrained_view_rect_max_y": 1724,
			"final_view_origin_minus_camera_component_x": 0,
			"final_view_origin_minus_camera_component_y": 0,
			"final_view_origin_minus_camera_component_z": 0,
			"final_view_origin_minus_player_camera_manager_x": 0,
			"final_view_origin_minus_player_camera_manager_y": 0,
			"final_view_origin_minus_player_camera_manager_z": 0
		},
		"perspective_restored_rendered_frame":
		{
			"stage": "perspective_restored_rendered_frame",
			"pawn_transform":
			{
				"location_x": -306.15092432089057,
				"location_y": -402.36520922524483,
				"location_z": 379.13568198893745,
				"pitch": 0,
				"yaw": 63.902479999999954,
				"roll": 0,
				"scale_x": 1,
				"scale_y": 1,
				"scale_z": 1
			},
			"camera_component_transform":
			{
				"location_x": -671.31718871997953,
				"location_y": -1502.4524285263358,
				"location_z": 689.7185361119632,
				"pitch": -15.000000000000018,
				"yaw": 71.636774675290539,
				"roll": -8.2318812555273957e-16,
				"scale_x": 1,
				"scale_y": 1,
				"scale_z": 1
			},
			"camera_component_projection":
			{
				"projection_mode": "ECameraProjectionMode::Perspective",
				"field_of_view": 90,
				"ortho_width": 1536,
				"ortho_near_clip_plane": -768,
				"ortho_far_clip_plane": 2097152,
				"auto_plane_shift": 0,
				"aspect_ratio": 1.7777780294418335,
				"auto_calculate_ortho_planes": true,
				"update_ortho_planes": true,
				"use_camera_height_as_view_target": true,
				"constrain_aspect_ratio": false
			},
			"camera_boom_available": true,
			"camera_boom_transform":
			{
				"location_x": -306.15092432089057,
				"location_y": -402.36520922524483,
				"location_z": 379.13568198893745,
				"pitch": -15.000000000000046,
				"yaw": 71.636774675290667,
				"roll": 0,
				"scale_x": 1,
				"scale_y": 1,
				"scale_z": 1
			},
			"player_camera_manager_available": true,
			"player_camera_manager_view":
			{
				"transform":
				{
					"location_x": -671.31718871997953,
					"location_y": -1502.4524285263358,
					"location_z": 689.7185361119632,
					"pitch": -15.000000000000009,
					"yaw": 71.636774675290468,
					"roll": 8.2318812555273957e-16,
					"scale_x": 1,
					"scale_y": 1,
					"scale_z": 1
				},
				"projection_mode": "ECameraProjectionMode::Perspective",
				"field_of_view": 90,
				"ortho_width": 1536,
				"ortho_near_clip_plane": -768,
				"ortho_far_clip_plane": 2097152,
				"auto_plane_shift": 0,
				"aspect_ratio": 1.7777780294418335,
				"auto_calculate_ortho_planes": true,
				"update_ortho_planes": true,
				"use_camera_height_as_view_target": true,
				"constrain_aspect_ratio": false
			},
			"projection_data_available": true,
			"final_view_origin":
			{
				"value_x": -671.31718871997953,
				"value_y": -1502.4524285263358,
				"value_z": 689.7185361119632
			},
			"camera_to_view_target":
			{
				"value_x": 0,
				"value_y": 0,
				"value_z": 0
			},
			"final_view_rotation_matrix":
			{
				"row_0": [
					-0.94907842305774293,
					0.081538331711158818,
					0.3043051878427136,
					0
				],
				"row_1": [
					0.31503991316375796,
					0.24563957786187021,
					0.91673935821563513,
					0
				],
				"row_2": [
					1.3877788166908646e-17,
					0.9659258244035116,
					-0.25881905213951456,
					0
				],
				"row_3": [
					0,
					0,
					0,
					1
				]
			},
			"final_projection_matrix":
			{
				"row_0": [
					1.1897861714690126,
					0,
					0,
					0
				],
				"row_1": [
					0,
					1.7777779394035089,
					0,
					0
				],
				"row_2": [
					0,
					0,
					0,
					1
				],
				"row_3": [
					0,
					0,
					10,
					0
				]
			},
			"view_rect_min_x": 0,
			"view_rect_min_y": 0,
			"view_rect_max_x": 2576,
			"view_rect_max_y": 1724,
			"constrained_view_rect_min_x": 0,
			"constrained_view_rect_min_y": 0,
			"constrained_view_rect_max_x": 2576,
			"constrained_view_rect_max_y": 1724,
			"final_view_origin_minus_camera_component_x": 0,
			"final_view_origin_minus_camera_component_y": 0,
			"final_view_origin_minus_camera_component_z": 0,
			"final_view_origin_minus_player_camera_manager_x": 0,
			"final_view_origin_minus_player_camera_manager_y": 0,
			"final_view_origin_minus_player_camera_manager_z": 0
		}
	},
	"deltas":
	{
		"switch_perspective_to_first_orthographic":
		{
			"from_stage": "perspective_before_switch",
			"to_stage": "orthographic_first_rendered_frame",
			"camera_component_transform_delta":
			{
				"location_delta_x": 0,
				"location_delta_y": 0,
				"location_delta_z": 0,
				"location_distance": 0,
				"pitch_delta": 0,
				"yaw_delta": 0,
				"roll_delta": 0,
				"scale_delta_x": 0,
				"scale_delta_y": 0,
				"scale_delta_z": 0
			},
			"camera_component_pose_unchanged": true,
			"player_camera_manager_transform_delta":
			{
				"location_delta_x": 0,
				"location_delta_y": 0,
				"location_delta_z": 0,
				"location_distance": 0,
				"pitch_delta": 0,
				"yaw_delta": 0,
				"roll_delta": 0,
				"scale_delta_x": 0,
				"scale_delta_y": 0,
				"scale_delta_z": 0
			},
			"player_camera_manager_pose_unchanged": true,
			"final_view_origin_delta":
			{
				"delta_x": 0,
				"delta_y": 0,
				"delta_z": 0,
				"distance": 0
			},
			"final_view_origin_unchanged": true
		},
		"orthographic_first_to_stable":
		{
			"from_stage": "orthographic_first_rendered_frame",
			"to_stage": "orthographic_stable_after_wait",
			"camera_component_transform_delta":
			{
				"location_delta_x": 0,
				"location_delta_y": 0,
				"location_delta_z": 0,
				"location_distance": 0,
				"pitch_delta": 0,
				"yaw_delta": 0,
				"roll_delta": 0,
				"scale_delta_x": 0,
				"scale_delta_y": 0,
				"scale_delta_z": 0
			},
			"camera_component_pose_unchanged": true,
			"player_camera_manager_transform_delta":
			{
				"location_delta_x": 0,
				"location_delta_y": 0,
				"location_delta_z": 0,
				"location_distance": 0,
				"pitch_delta": 0,
				"yaw_delta": 0,
				"roll_delta": 0,
				"scale_delta_x": 0,
				"scale_delta_y": 0,
				"scale_delta_z": 0
			},
			"player_camera_manager_pose_unchanged": true,
			"final_view_origin_delta":
			{
				"delta_x": 0,
				"delta_y": 0,
				"delta_z": 0,
				"distance": 0
			},
			"final_view_origin_unchanged": true
		},
		"full_cycle_perspective_before_to_restored":
		{
			"from_stage": "perspective_before_switch",
			"to_stage": "perspective_restored_rendered_frame",
			"camera_component_transform_delta":
			{
				"location_delta_x": 0,
				"location_delta_y": 0,
				"location_delta_z": 0,
				"location_distance": 0,
				"pitch_delta": 0,
				"yaw_delta": 0,
				"roll_delta": 0,
				"scale_delta_x": 0,
				"scale_delta_y": 0,
				"scale_delta_z": 0
			},
			"camera_component_pose_unchanged": true,
			"player_camera_manager_transform_delta":
			{
				"location_delta_x": 0,
				"location_delta_y": 0,
				"location_delta_z": 0,
				"location_distance": 0,
				"pitch_delta": 0,
				"yaw_delta": 0,
				"roll_delta": 0,
				"scale_delta_x": 0,
				"scale_delta_y": 0,
				"scale_delta_z": 0
			},
			"player_camera_manager_pose_unchanged": true,
			"final_view_origin_delta":
			{
				"delta_x": 0,
				"delta_y": 0,
				"delta_z": 0,
				"distance": 0
			},
			"final_view_origin_unchanged": true
		}
	},
	"validation":
	{
		"switch_camera_component_pose_unchanged": true,
		"switch_final_view_origin_unchanged": true,
		"restored_camera_component_pose_matches_before": true,
		"restored_final_view_origin_matches_before": true,
		"orthographic_auto_origin_shift_prevented": true,
		"scene_capture_uses_stable_viewport_projection_matrix": true
	}
}